TADGATE/Call_TADs.py
TADGATE/Plot_Function.py
TADGATE/TADGATE_CLI.py
TADGATE/TADGATE_main.py
TADGATE/TADGATE_pyG.py
TADGATE/TADGATE_utils.py
TADGATE/__init__.py
TADGATE/gat_conv.py
TADGATE-2.0.0.dist-info/METADATA
TADGATE-2.0.0.dist-info/WHEEL
TADGATE-2.0.0.dist-info/top_level.txt
TADGATE-2.0.0.dist-info/RECORD
